{
  "id": "3614278",
  "name": "Drome",
  "font_family": "iconfont",
  "css_prefix_text": "icon-",
  "description": "循迹科技",
  "glyphs": [
    {
      "icon_id": "21378798",
      "name": "success",
      "font_class": "submit-success",
      "unicode": "e600",
      "unicode_decimal": 58880
    },
    {
      "icon_id": "12025550",
      "name": "close",
      "font_class": "close",
      "unicode": "e602",
      "unicode_decimal": 58882
    },
    {
      "icon_id": "33215705",
      "name": "solution-flight-takeoff-line",
      "font_class": "solution-flight-takeoff-line",
      "unicode": "e61d",
      "unicode_decimal": 58909
    },
    {
      "icon_id": "33215706",
      "name": "solution-cellphone-line",
      "font_class": "solution-cellphone-line",
      "unicode": "e61e",
      "unicode_decimal": 58910
    },
    {
      "icon_id": "33215707",
      "name": "solution-terminal-box-line",
      "font_class": "solution-terminal-box-line",
      "unicode": "e61f",
      "unicode_decimal": 58911
    },
    {
      "icon_id": "33215708",
      "name": "solution-medicine-bottle-line",
      "font_class": "solution-medicine-bottle-line",
      "unicode": "e620",
      "unicode_decimal": 58912
    },
    {
      "icon_id": "33215709",
      "name": "solution-roadster-line",
      "font_class": "solution-roadster-line",
      "unicode": "e621",
      "unicode_decimal": 58913
    },
    {
      "icon_id": "33091278",
      "name": "icon-quality",
      "font_class": "quality",
      "unicode": "e61c",
      "unicode_decimal": 58908
    },
    {
      "icon_id": "33091215",
      "name": "icon-developm",
      "font_class": "developm",
      "unicode": "e61b",
      "unicode_decimal": 58907
    },
    {
      "icon_id": "31546932",
      "name": "map-pin-fill",
      "font_class": "map-pin-fill",
      "unicode": "e618",
      "unicode_decimal": 58904
    },
    {
      "icon_id": "31546933",
      "name": "mail-fill",
      "font_class": "mail-fill",
      "unicode": "e619",
      "unicode_decimal": 58905
    },
    {
      "icon_id": "31546934",
      "name": "phone-fill",
      "font_class": "phone-fill",
      "unicode": "e61a",
      "unicode_decimal": 58906
    },
    {
      "icon_id": "16165423",
      "name": "下载",
      "font_class": "download",
      "unicode": "e653",
      "unicode_decimal": 58963
    },
    {
      "icon_id": "964425",
      "name": "勾",
      "font_class": "gougou",
      "unicode": "e6a3",
      "unicode_decimal": 59043
    },
    {
      "icon_id": "31508857",
      "name": "requirement",
      "font_class": "requirement",
      "unicode": "e615",
      "unicode_decimal": 58901
    },
    {
      "icon_id": "31508858",
      "name": "code",
      "font_class": "code",
      "unicode": "e616",
      "unicode_decimal": 58902
    },
    {
      "icon_id": "31508859",
      "name": "risk",
      "font_class": "risk",
      "unicode": "e617",
      "unicode_decimal": 58903
    }
  ]
}
